kospellpy/__init__.py
kospellpy/naver_spell_check.py
kospellpy/pusan_spell_check.py
kospellpy/spell_select.py
kospellpy-0.0.3.dist-info/LICENSE
kospellpy-0.0.3.dist-info/METADATA
kospellpy-0.0.3.dist-info/WHEEL
kospellpy-0.0.3.dist-info/top_level.txt
kospellpy-0.0.3.dist-info/RECORD
