Metadata-Version: 2.1
Name: kospellpy
Version: 0.0.3
Summary: Korean Spell Checker
Home-page: https://github.com/Kangsukmin/koSpellPy
Author: decyma
Author-email: soos3121@gmail.com
License: MIT
Platform: UNKNOWN
Classifier: Programming Language :: Python :: 3
Classifier: License :: OSI Approved :: MIT License
Classifier: Operating System :: OS Independent
Requires-Python: >=3.6
License-File: LICENSE
Requires-Dist: requests (==2.26.0)
